{
"meta":{"test_sets":[],"test_metrics":[],"learn_metrics":[{"best_value":"Min","name":"RMSE"}],"launch_mode":"Train","parameters":"","iteration_count":100,"learn_sets":["learn"],"name":"experiment"},
"iterations":[
{"learn":[185.0098022],"iteration":0,"passed_time":0.0181343113,"remaining_time":1.795296819},
{"learn":[171.0311857],"iteration":1,"passed_time":0.03173977601,"remaining_time":1.555249024},
{"learn":[157.8556378],"iteration":2,"passed_time":0.04363978385,"remaining_time":1.411019678},
{"learn":[146.7121607],"iteration":3,"passed_time":0.05477972775,"remaining_time":1.314713466},
{"learn":[136.3499709],"iteration":4,"passed_time":0.06584519372,"remaining_time":1.251058681},
{"learn":[127.2485962],"iteration":5,"passed_time":0.07660074631,"remaining_time":1.200078359},
{"learn":[118.9877079],"iteration":6,"passed_time":0.08740035229,"remaining_time":1.161176109},
{"learn":[111.6430876],"iteration":7,"passed_time":0.09618877329,"remaining_time":1.106170893},
{"learn":[104.9527613],"iteration":8,"passed_time":0.1034281065,"remaining_time":1.045773076},
{"learn":[99.02932022],"iteration":9,"passed_time":0.1089690435,"remaining_time":0.9807213913},
{"learn":[93.82953363],"iteration":10,"passed_time":0.1139017396,"remaining_time":0.9215686204},
{"learn":[89.14752098],"iteration":11,"passed_time":0.1187888948,"remaining_time":0.8711185615},
{"learn":[85.17910747],"iteration":12,"passed_time":0.1236302826,"remaining_time":0.8273718912},
{"learn":[81.59914426],"iteration":13,"passed_time":0.1284628733,"remaining_time":0.7891290788},
{"learn":[78.33877001],"iteration":14,"passed_time":0.1341305504,"remaining_time":0.7600731191},
{"learn":[75.51776198],"iteration":15,"passed_time":0.1390664532,"remaining_time":0.7300988795},
{"learn":[72.97999445],"iteration":16,"passed_time":0.1438829758,"remaining_time":0.7024874701},
{"learn":[70.83509683],"iteration":17,"passed_time":0.1491797461,"remaining_time":0.6795966212},
{"learn":[68.96502726],"iteration":18,"passed_time":0.1538118866,"remaining_time":0.6557243587},
{"learn":[67.2594358],"iteration":19,"passed_time":0.1585205385,"remaining_time":0.634082154},
{"learn":[65.70516264],"iteration":20,"passed_time":0.1633214807,"remaining_time":0.6143998559},
{"learn":[64.32293814],"iteration":21,"passed_time":0.1678838978,"remaining_time":0.5952247286},
{"learn":[63.2011844],"iteration":22,"passed_time":0.1726634142,"remaining_time":0.5780470824},
{"learn":[62.07512933],"iteration":23,"passed_time":0.1774721785,"remaining_time":0.5619952318},
{"learn":[61.09750252],"iteration":24,"passed_time":0.1822275571,"remaining_time":0.5466826714},
{"learn":[60.07997961],"iteration":25,"passed_time":0.1867958682,"remaining_time":0.5316497788},
{"learn":[59.23198294],"iteration":26,"passed_time":0.1916473557,"remaining_time":0.5181576653},
{"learn":[58.47353914],"iteration":27,"passed_time":0.196591518,"remaining_time":0.5055210463},
{"learn":[57.80249168],"iteration":28,"passed_time":0.20138802,"remaining_time":0.4930534283},
{"learn":[57.15510147],"iteration":29,"passed_time":0.2058751094,"remaining_time":0.4803752552},
{"learn":[56.55746962],"iteration":30,"passed_time":0.2105556784,"remaining_time":0.4686561875},
{"learn":[56.03538033],"iteration":31,"passed_time":0.2152819489,"remaining_time":0.4574741414},
{"learn":[55.56907758],"iteration":32,"passed_time":0.2200533706,"remaining_time":0.4467750251},
{"learn":[55.10355428],"iteration":33,"passed_time":0.2247489672,"remaining_time":0.4362774069},
{"learn":[54.70927155],"iteration":34,"passed_time":0.2294539224,"remaining_time":0.4261287131},
{"learn":[54.30734083],"iteration":35,"passed_time":0.2341304016,"remaining_time":0.4162318251},
{"learn":[53.97638174],"iteration":36,"passed_time":0.2389364639,"remaining_time":0.4068377628},
{"learn":[53.63701318],"iteration":37,"passed_time":0.2435162524,"remaining_time":0.3973159908},
{"learn":[53.38048076],"iteration":38,"passed_time":0.2480796667,"remaining_time":0.3880220429},
{"learn":[53.12195754],"iteration":39,"passed_time":0.2529275443,"remaining_time":0.3793913164},
{"learn":[52.86055724],"iteration":40,"passed_time":0.2576780496,"remaining_time":0.3708049982},
{"learn":[52.62976549],"iteration":41,"passed_time":0.2624411042,"remaining_time":0.3624186677},
{"learn":[52.40318883],"iteration":42,"passed_time":0.2670439163,"remaining_time":0.3539884471},
{"learn":[52.20854218],"iteration":43,"passed_time":0.2717976729,"remaining_time":0.345924311},
{"learn":[52.02900037],"iteration":44,"passed_time":0.276318084,"remaining_time":0.3377221026},
{"learn":[51.86344956],"iteration":45,"passed_time":0.2810233809,"remaining_time":0.3298970124},
{"learn":[51.69396463],"iteration":46,"passed_time":0.2855568684,"remaining_time":0.3220109367},
{"learn":[51.5505685],"iteration":47,"passed_time":0.2901364376,"remaining_time":0.3143144741},
{"learn":[51.41256638],"iteration":48,"passed_time":0.294638669,"remaining_time":0.3066647371},
{"learn":[51.28395423],"iteration":49,"passed_time":0.2997289924,"remaining_time":0.2997289924},
{"learn":[51.15823699],"iteration":50,"passed_time":0.3043631221,"remaining_time":0.2924273134},
{"learn":[51.04594192],"iteration":51,"passed_time":0.3095933029,"remaining_time":0.2857784335},
{"learn":[50.93947485],"iteration":52,"passed_time":0.3141957807,"remaining_time":0.278626447},
{"learn":[50.834025],"iteration":53,"passed_time":0.3188428282,"remaining_time":0.2716068536},
{"learn":[50.74300677],"iteration":54,"passed_time":0.3232965166,"remaining_time":0.2645153318},
{"learn":[50.65507792],"iteration":55,"passed_time":0.3279854236,"remaining_time":0.2577028329},
{"learn":[50.58754565],"iteration":56,"passed_time":0.3325107349,"remaining_time":0.2508414316},
{"learn":[50.50719708],"iteration":57,"passed_time":0.3371627087,"remaining_time":0.2441523063},
{"learn":[50.43801607],"iteration":58,"passed_time":0.3416550009,"remaining_time":0.2374212718},
{"learn":[50.37469079],"iteration":59,"passed_time":0.3464699049,"remaining_time":0.2309799366},
{"learn":[50.31886426],"iteration":60,"passed_time":0.3511388036,"remaining_time":0.2244985793},
{"learn":[50.2467668],"iteration":61,"passed_time":0.3557426345,"remaining_time":0.2180358083},
{"learn":[50.19195417],"iteration":62,"passed_time":0.3602405367,"remaining_time":0.211569839},
{"learn":[50.14712326],"iteration":63,"passed_time":0.3651654277,"remaining_time":0.2054055531},
{"learn":[50.09234889],"iteration":64,"passed_time":0.3698901655,"remaining_time":0.1991716276},
{"learn":[50.03726909],"iteration":65,"passed_time":0.3747208472,"remaining_time":0.1930380122},
{"learn":[49.98888153],"iteration":66,"passed_time":0.3793325257,"remaining_time":0.1868354231},
{"learn":[49.95103344],"iteration":67,"passed_time":0.3838218341,"remaining_time":0.1806220396},
{"learn":[49.90904826],"iteration":68,"passed_time":0.3883704724,"remaining_time":0.1744852847},
{"learn":[49.86976394],"iteration":69,"passed_time":0.3970363142,"remaining_time":0.1701584204},
{"learn":[49.83420038],"iteration":70,"passed_time":0.4041973437,"remaining_time":0.1650946897},
{"learn":[49.805381],"iteration":71,"passed_time":0.4088611435,"remaining_time":0.1590015558},
{"learn":[49.79118915],"iteration":72,"passed_time":0.4133312499,"remaining_time":0.1528759417},
{"learn":[49.76080361],"iteration":73,"passed_time":0.4180615404,"remaining_time":0.1468864872},
{"learn":[49.72937721],"iteration":74,"passed_time":0.42283355,"remaining_time":0.1409445167},
{"learn":[49.69760649],"iteration":75,"passed_time":0.4275130824,"remaining_time":0.1350041313},
{"learn":[49.66662786],"iteration":76,"passed_time":0.4320305009,"remaining_time":0.1290480717},
{"learn":[49.63901801],"iteration":77,"passed_time":0.4366523693,"remaining_time":0.1231583606},
{"learn":[49.61351159],"iteration":78,"passed_time":0.4412939963,"remaining_time":0.117305999},
{"learn":[49.58887206],"iteration":79,"passed_time":0.4458422365,"remaining_time":0.1114605591},
{"learn":[49.5666449],"iteration":80,"passed_time":0.4504281775,"remaining_time":0.1056559922},
{"learn":[49.54585082],"iteration":81,"passed_time":0.4549863603,"remaining_time":0.09987505471},
{"learn":[49.52755392],"iteration":82,"passed_time":0.45968927,"remaining_time":0.09415322397},
{"learn":[49.51188978],"iteration":83,"passed_time":0.4650592565,"remaining_time":0.08858271553},
{"learn":[49.49764078],"iteration":84,"passed_time":0.4696393191,"remaining_time":0.0828775269},
{"learn":[49.48393553],"iteration":85,"passed_time":0.4746210777,"remaining_time":0.07726389637},
{"learn":[49.46803683],"iteration":86,"passed_time":0.4793380663,"remaining_time":0.07162522829},
{"learn":[49.45248373],"iteration":87,"passed_time":0.4838461899,"remaining_time":0.0659790259},
{"learn":[49.43820293],"iteration":88,"passed_time":0.4890599995,"remaining_time":0.06044561791},
{"learn":[49.42070194],"iteration":89,"passed_time":0.4945388439,"remaining_time":0.05494876044},
{"learn":[49.39878457],"iteration":90,"passed_time":0.5048278652,"remaining_time":0.04992803063},
{"learn":[49.38311569],"iteration":91,"passed_time":0.5109896509,"remaining_time":0.04443388269},
{"learn":[49.3663388],"iteration":92,"passed_time":0.5180531568,"remaining_time":0.03899324836},
{"learn":[49.3521267],"iteration":93,"passed_time":0.5245289679,"remaining_time":0.03348057242},
{"learn":[49.33423997],"iteration":94,"passed_time":0.5302552426,"remaining_time":0.02790817066},
{"learn":[49.32331901],"iteration":95,"passed_time":0.5359977501,"remaining_time":0.02233323959},
{"learn":[49.30767778],"iteration":96,"passed_time":0.5423799437,"remaining_time":0.01677463743},
{"learn":[49.29649938],"iteration":97,"passed_time":0.5485191131,"remaining_time":0.01119426761},
{"learn":[49.28547096],"iteration":98,"passed_time":0.5543958845,"remaining_time":0.005599958429},
{"learn":[49.27242776],"iteration":99,"passed_time":0.5594291253,"remaining_time":0}
]}